.gitignore
README.md
requirements.txt
setup.py
src/python_logging_proxy/__init__.py
src/python_logging_proxy/handlers.py
src/python_logging_proxy/logging_proxy.py
src/python_logging_proxy/micro_orm.py
src/python_logging_proxy/version.txt
src/python_logging_proxy.egg-info/PKG-INFO
src/python_logging_proxy.egg-info/SOURCES.txt
src/python_logging_proxy.egg-info/dependency_links.txt
src/python_logging_proxy.egg-info/requires.txt
src/python_logging_proxy.egg-info/top_level.txt