Metadata-Version: 1.1
Name: python-logging-proxy
Version: 1.0.7
Summary: Logging Proxy adapting pymiproxy
Home-page: https://github.com/alistair-broomhead/python-logging-proxy
Author: Alistair Broomhead
Author-email: alistair.broomhead@gmail.com
License: MIT
Download-URL: https://github.com/alistair-broomhead/python-logging-proxy/zipball/master
Platform: UNKNOWN
